benny_kubernetes/__init__.py
benny_kubernetes/api_client.py
benny_kubernetes/api_response.py
benny_kubernetes/configuration.py
benny_kubernetes/exceptions.py
benny_kubernetes/py.typed
benny_kubernetes/rest.py
benny_kubernetes/api/__init__.py
benny_kubernetes/api/admissionregistration_api.py
benny_kubernetes/api/admissionregistration_v1_api.py
benny_kubernetes/api/admissionregistration_v1beta1_api.py
benny_kubernetes/api/apiextensions_api.py
benny_kubernetes/api/apiextensions_v1_api.py
benny_kubernetes/api/apiextensions_v1beta1_api.py
benny_kubernetes/api/apiregistration_api.py
benny_kubernetes/api/apiregistration_v1_api.py
benny_kubernetes/api/apiregistration_v1beta1_api.py
benny_kubernetes/api/apis_api.py
benny_kubernetes/api/apps_api.py
benny_kubernetes/api/apps_v1_api.py
benny_kubernetes/api/auditregistration_api.py
benny_kubernetes/api/auditregistration_v1alpha1_api.py
benny_kubernetes/api/authentication_api.py
benny_kubernetes/api/authentication_v1_api.py
benny_kubernetes/api/authentication_v1beta1_api.py
benny_kubernetes/api/authorization_api.py
benny_kubernetes/api/authorization_v1_api.py
benny_kubernetes/api/authorization_v1beta1_api.py
benny_kubernetes/api/autoscaling_api.py
benny_kubernetes/api/autoscaling_v1_api.py
benny_kubernetes/api/autoscaling_v2beta1_api.py
benny_kubernetes/api/autoscaling_v2beta2_api.py
benny_kubernetes/api/batch_api.py
benny_kubernetes/api/batch_v1_api.py
benny_kubernetes/api/batch_v1beta1_api.py
benny_kubernetes/api/batch_v2alpha1_api.py
benny_kubernetes/api/certificates_api.py
benny_kubernetes/api/certificates_v1beta1_api.py
benny_kubernetes/api/coordination_api.py
benny_kubernetes/api/coordination_v1_api.py
benny_kubernetes/api/coordination_v1beta1_api.py
benny_kubernetes/api/core_api.py
benny_kubernetes/api/core_v1_api.py
benny_kubernetes/api/discovery_api.py
benny_kubernetes/api/discovery_v1beta1_api.py
benny_kubernetes/api/events_api.py
benny_kubernetes/api/events_v1beta1_api.py
benny_kubernetes/api/extensions_api.py
benny_kubernetes-2.0.0.dist-info/METADATA
benny_kubernetes-2.0.0.dist-info/WHEEL
benny_kubernetes-2.0.0.dist-info/top_level.txt
benny_kubernetes-2.0.0.dist-info/RECORD
