Metadata-Version: 2.1
Name: benny-kubernetes
Version: 2.0.0
Summary: Kubernetes
Home-page: 
Author: OpenAPI Generator community
Author-email: team@openapitools.org
Keywords: OpenAPI,OpenAPI-Generator,Kubernetes
Requires-Dist: urllib3 (<2.1.0,>=1.25.3)
Requires-Dist: python-dateutil
Requires-Dist: pydantic (<2,>=1.10.5)
Requires-Dist: aenum
